{
    "sites": [
        { "name": "森林资源|AV", "type": 1, "api": "https://slapibf.com/api.php/provide/vod/" },
        { "name": "91视频|AV", "type": 1, "api": "https://91av.cyou/api.php/provide/vod/" },
        { "name": "奥斯卡资源|AV", "type": 1, "api": "https://aosikazy.com/api.php/provide/vod/" },
        { "name": "91麻豆|AV", "type": 1, "api": "https://91md.me/api.php/provide/vod/" },
        { "name": "番号资源|AV", "type": 1, "api": "http://fhapi9.com/api.php/provide/vod/" },
        { "name": "鲨鱼资源|AV", "type": 1, "api": "https://shayuapi.com/api.php/provide/vod/" },
        { "name": "AIvin|AV", "type": 1, "api": "http://lbapiby.com/api.php/provide/vod/at/json" },
        { "name": "玉兔资源|AV", "type": 1, "api": "https://apiyutu.com/api.php/provide/vod/" },
        { "name": "奶香香|AV", "type": 1, "api": "https://Naixxzy.com/api.php/provide/vod/" },
        { "name": "精品资源|AV", "type": 1, "api": "https://www.jingpinx.com/api.php/provide/vod/" },
        { "name": "X细胞资源|AV", "type": 1, "api": "https://www.xxibaozyw.com/api.php/provide/vod/" },
        { "name": "老色逼资源|AV", "type": 1, "api": "https://apilsbzy1.com/api.php/provide/vod/" }
    ]
}
